MANIFEST.in
setup.py
advanced_jabberclient/README.txt
advanced_jabberclient/__init__.py
advanced_jabberclient/jabberclient.py
advanced_jabberclient.egg-info/PKG-INFO
advanced_jabberclient.egg-info/SOURCES.txt
advanced_jabberclient.egg-info/dependency_links.txt
advanced_jabberclient.egg-info/requires.txt
advanced_jabberclient.egg-info/top_level.txt
advanced_jabberclient/advanced_jabberclient.egg-info/PKG-INFO
advanced_jabberclient/advanced_jabberclient.egg-info/SOURCES.txt
advanced_jabberclient/advanced_jabberclient.egg-info/dependency_links.txt
advanced_jabberclient/advanced_jabberclient.egg-info/requires.txt
advanced_jabberclient/advanced_jabberclient.egg-info/top_level.txt
advanced_jabberclient/dist/advanced_jabberclient-1.0.0.tar.gz