Metadata-Version: 1.0
Name: advanced_jabberclient
Version: 1.0.0
Summary: Advanced jabber client with ping timeouts
Home-page: https://github.com/ruscoder/advanced_jabberclient
Author: Vadim
Author-email: Vadim <rusmiligamer@gmail.com>
License: BSD
Keywords: twisted module jabber client ping timeout
Platform: UNKNOWN
